CHANGELOG.rst
README.rst
django_copyist/__init__.py
django_copyist/config.py
django_copyist/copy_request.py
django_copyist/copyist.py
django_copyist-0.1.3.dist-info/LICENSE.txt
django_copyist-0.1.3.dist-info/METADATA
django_copyist-0.1.3.dist-info/WHEEL
django_copyist-0.1.3.dist-info/RECORD
