Metadata-Version: 2.1
Name: django-copyist
Version: 0.1.3
Summary: Tool for precise and efficient django model copying
Home-page: https://github.com/abondar/django-copyist
License: Apache-2.0
Keywords: django,copy,clone,model
Author: abondar
Requires-Python: >=3.11,<4.0
Classifier: License :: OSI Approved :: Apache Software License
Classifier: Programming Language :: Python :: 3
Classifier: Programming Language :: Python :: 3.11
Classifier: Programming Language :: Python :: 3.12
Requires-Dist: Django (>=3.2)
Project-URL: Documentation, https://abondar.github.io/django-copyist/
Project-URL: Repository, https://github.com/abondar/django-copyist.git
